{
  "frames": {
    "idle_00": {
      "frame": {
        "x": 0,
        "y": 0,
        "w": 103,
        "h": 79
      },
      "trimmed": true,
      "spriteSourceSize": {
        "x": 259,
        "y": 765,
        "w": 103,
        "h": 79
      },
      "sourceSize": {
        "w": 544,
        "h": 1013
      }
    },
    "idle_01": {
      "frame": {
        "x": 103,
        "y": 0,
        "w": 103,
        "h": 79
      },
      "trimmed": true,
      "spriteSourceSize": {
        "x": 259,
        "y": 768,
        "w": 103,
        "h": 79
      },
      "sourceSize": {
        "w": 544,
        "h": 1013
      }
    },
    "idle_02": {
      "frame": {
        "x": 206,
        "y": 0,
        "w": 103,
        "h": 79
      },
      "trimmed": true,
      "spriteSourceSize": {
        "x": 259,
        "y": 769,
        "w": 103,
        "h": 79
      },
      "sourceSize": {
        "w": 544,
        "h": 1013
      }
    },
    "idle_03": {
      "frame": {
        "x": 309,
        "y": 0,
        "w": 103,
        "h": 79
      },
      "trimmed": true,
      "spriteSourceSize": {
        "x": 259,
        "y": 769,
        "w": 103,
        "h": 79
      },
      "sourceSize": {
        "w": 544,
        "h": 1013
      }
    },
    "idle_04": {
      "frame": {
        "x": 412,
        "y": 0,
        "w": 103,
        "h": 79
      },
      "trimmed": true,
      "spriteSourceSize": {
        "x": 259,
        "y": 769,
        "w": 103,
        "h": 79
      },
      "sourceSize": {
        "w": 544,
        "h": 1013
      }
    },
    "idle_05": {
      "frame": {
        "x": 515,
        "y": 0,
        "w": 103,
        "h": 79
      },
      "trimmed": true,
      "spriteSourceSize": {
        "x": 259,
        "y": 769,
        "w": 103,
        "h": 79
      },
      "sourceSize": {
        "w": 544,
        "h": 1013
      }
    },
    "idle_06": {
      "frame": {
        "x": 618,
        "y": 0,
        "w": 103,
        "h": 79
      },
      "trimmed": true,
      "spriteSourceSize": {
        "x": 259,
        "y": 768,
        "w": 103,
        "h": 79
      },
      "sourceSize": {
        "w": 544,
        "h": 1013
      }
    },
    "idle_07": {
      "frame": {
        "x": 721,
        "y": 0,
        "w": 103,
        "h": 79
      },
      "trimmed": true,
      "spriteSourceSize": {
        "x": 258,
        "y": 766,
        "w": 103,
        "h": 79
      },
      "sourceSize": {
        "w": 544,
        "h": 1013
      }
    },
    "walking_00": {
      "frame": {
        "x": 824,
        "y": 0,
        "w": 103,
        "h": 79
      },
      "trimmed": true,
      "spriteSourceSize": {
        "x": 259,
        "y": 765,
        "w": 103,
        "h": 79
      },
      "sourceSize": {
        "w": 544,
        "h": 1013
      }
    },
    "walking_01": {
      "frame": {
        "x": 927,
        "y": 0,
        "w": 103,
        "h": 79
      },
      "trimmed": true,
      "spriteSourceSize": {
        "x": 259,
        "y": 758,
        "w": 103,
        "h": 79
      },
      "sourceSize": {
        "w": 544,
        "h": 1013
      }
    },
    "walking_02": {
      "frame": {
        "x": 1030,
        "y": 0,
        "w": 103,
        "h": 79
      },
      "trimmed": true,
      "spriteSourceSize": {
        "x": 259,
        "y": 749,
        "w": 103,
        "h": 79
      },
      "sourceSize": {
        "w": 544,
        "h": 1013
      }
    },
    "walking_03": {
      "frame": {
        "x": 1133,
        "y": 0,
        "w": 103,
        "h": 79
      },
      "trimmed": true,
      "spriteSourceSize": {
        "x": 259,
        "y": 757,
        "w": 103,
        "h": 79
      },
      "sourceSize": {
        "w": 544,
        "h": 1013
      }
    },
    "walking_04": {
      "frame": {
        "x": 1236,
        "y": 0,
        "w": 103,
        "h": 79
      },
      "trimmed": true,
      "spriteSourceSize": {
        "x": 259,
        "y": 765,
        "w": 103,
        "h": 79
      },
      "sourceSize": {
        "w": 544,
        "h": 1013
      }
    },
    "walking_05": {
      "frame": {
        "x": 1339,
        "y": 0,
        "w": 103,
        "h": 79
      },
      "trimmed": true,
      "spriteSourceSize": {
        "x": 259,
        "y": 758,
        "w": 103,
        "h": 79
      },
      "sourceSize": {
        "w": 544,
        "h": 1013
      }
    },
    "walking_06": {
      "frame": {
        "x": 1442,
        "y": 0,
        "w": 103,
        "h": 79
      },
      "trimmed": true,
      "spriteSourceSize": {
        "x": 259,
        "y": 749,
        "w": 103,
        "h": 79
      },
      "sourceSize": {
        "w": 544,
        "h": 1013
      }
    },
    "walking_07": {
      "frame": {
        "x": 1545,
        "y": 0,
        "w": 103,
        "h": 79
      },
      "trimmed": true,
      "spriteSourceSize": {
        "x": 258,
        "y": 757,
        "w": 103,
        "h": 79
      },
      "sourceSize": {
        "w": 544,
        "h": 1013
      }
    },
    "jumping_00": {
      "frame": {
        "x": 1648,
        "y": 0,
        "w": 103,
        "h": 79
      },
      "trimmed": true,
      "spriteSourceSize": {
        "x": 311,
        "y": 745,
        "w": 103,
        "h": 79
      },
      "sourceSize": {
        "w": 544,
        "h": 1013
      }
    },
    "jumping_01": {
      "frame": {
        "x": 1751,
        "y": 0,
        "w": 103,
        "h": 79
      },
      "trimmed": true,
      "spriteSourceSize": {
        "x": 314,
        "y": 744,
        "w": 103,
        "h": 79
      },
      "sourceSize": {
        "w": 544,
        "h": 1013
      }
    },
    "jumping_02": {
      "frame": {
        "x": 1854,
        "y": 0,
        "w": 103,
        "h": 79
      },
      "trimmed": true,
      "spriteSourceSize": {
        "x": 318,
        "y": 743,
        "w": 103,
        "h": 79
      },
      "sourceSize": {
        "w": 544,
        "h": 1013
      }
    },
    "jumping_03": {
      "frame": {
        "x": 1957,
        "y": 0,
        "w": 103,
        "h": 79
      },
      "trimmed": true,
      "spriteSourceSize": {
        "x": 321,
        "y": 742,
        "w": 103,
        "h": 79
      },
      "sourceSize": {
        "w": 544,
        "h": 1013
      }
    },
    "jumping_04": {
      "frame": {
        "x": 2060,
        "y": 0,
        "w": 103,
        "h": 79
      },
      "trimmed": true,
      "spriteSourceSize": {
        "x": 323,
        "y": 742,
        "w": 103,
        "h": 79
      },
      "sourceSize": {
        "w": 544,
        "h": 1013
      }
    },
    "jumping_05": {
      "frame": {
        "x": 2163,
        "y": 0,
        "w": 103,
        "h": 79
      },
      "trimmed": true,
      "spriteSourceSize": {
        "x": 324,
        "y": 741,
        "w": 103,
        "h": 79
      },
      "sourceSize": {
        "w": 544,
        "h": 1013
      }
    },
    "jumping_06": {
      "frame": {
        "x": 2266,
        "y": 0,
        "w": 103,
        "h": 79
      },
      "trimmed": true,
      "spriteSourceSize": {
        "x": 325,
        "y": 741,
        "w": 103,
        "h": 79
      },
      "sourceSize": {
        "w": 544,
        "h": 1013
      }
    },
    "falling_00": {
      "frame": {
        "x": 2369,
        "y": 0,
        "w": 103,
        "h": 79
      },
      "trimmed": true,
      "spriteSourceSize": {
        "x": 325,
        "y": 741,
        "w": 103,
        "h": 79
      },
      "sourceSize": {
        "w": 544,
        "h": 1013
      }
    },
    "falling_01": {
      "frame": {
        "x": 2472,
        "y": 0,
        "w": 103,
        "h": 79
      },
      "trimmed": true,
      "spriteSourceSize": {
        "x": 321,
        "y": 741,
        "w": 103,
        "h": 79
      },
      "sourceSize": {
        "w": 544,
        "h": 1013
      }
    },
    "falling_02": {
      "frame": {
        "x": 2575,
        "y": 0,
        "w": 103,
        "h": 79
      },
      "trimmed": true,
      "spriteSourceSize": {
        "x": 305,
        "y": 740,
        "w": 103,
        "h": 79
      },
      "sourceSize": {
        "w": 544,
        "h": 1013
      }
    },
    "falling_03": {
      "frame": {
        "x": 2678,
        "y": 0,
        "w": 103,
        "h": 79
      },
      "trimmed": true,
      "spriteSourceSize": {
        "x": 279,
        "y": 740,
        "w": 103,
        "h": 79
      },
      "sourceSize": {
        "w": 544,
        "h": 1013
      }
    },
    "falling_04": {
      "frame": {
        "x": 2781,
        "y": 0,
        "w": 103,
        "h": 79
      },
      "trimmed": true,
      "spriteSourceSize": {
        "x": 251,
        "y": 738,
        "w": 103,
        "h": 79
      },
      "sourceSize": {
        "w": 544,
        "h": 1013
      }
    },
    "falling_05": {
      "frame": {
        "x": 2884,
        "y": 0,
        "w": 103,
        "h": 79
      },
      "trimmed": true,
      "spriteSourceSize": {
        "x": 232,
        "y": 737,
        "w": 103,
        "h": 79
      },
      "sourceSize": {
        "w": 544,
        "h": 1013
      }
    }
  },
  "animations": {
    "idle": [
      "idle_00",
      "idle_01",
      "idle_02",
      "idle_03",
      "idle_04",
      "idle_05",
      "idle_06",
      "idle_07"
    ],
    "walking": [
      "walking_00",
      "walking_01",
      "walking_02",
      "walking_03",
      "walking_04",
      "walking_05",
      "walking_06",
      "walking_07"
    ],
    "jumping": [
      "jumping_00",
      "jumping_01",
      "jumping_02",
      "jumping_03",
      "jumping_04",
      "jumping_05",
      "jumping_06"
    ],
    "falling": [
      "falling_00",
      "falling_01",
      "falling_02",
      "falling_03",
      "falling_04",
      "falling_05"
    ]
  },
  "meta": {
    "image": "Flower_Skirt.skirt.png",
    "format": "RGBA8888",
    "size": {
      "w": 2987,
      "h": 79
    },
    "scale": 1
  }
}